{
    "code":0,
    "info":"查询成功!",
    "retObj":{
        "data":[
            {
                "goodName":"佳迪沙琪玛",
                "imagePath":"image/r1.jpg",
                "price":"￥9.9",
                "marketPrice":"￥29.9"
            },
            {
                "goodName":"【12支散装】【约160g】雀巢脆脆鲨威",
                "imagePath":"image/r2.jpg",
                "price":"￥9.9",
                "marketPrice":"￥29.9"
            },
            {
                "goodName":"【甜辣味】【3包装】卫龙大面筋65g/包",
                "imagePath":"image/r3.jpg",
                "price":"￥9.9",
                "marketPrice":"￥29.9"
            },
            {
                "goodName":"【混合散装】金伯诺燕麦巧克力",
                "imagePath":"image/r4.jpg",
                "price":"￥9.9",
                "marketPrice":"￥29.9"
            },
            {
                "goodName":"【鸡蛋味】【散称装】白鹤鸡蛋煎饼250g",
                "imagePath":"image/r5.jpg",
                "price":"￥9.9",
                "marketPrice":"￥29.9"
            },
            {
                "goodName":"【奶香味】【散称装】盼盼法式小面包",
                "imagePath":"image/r6.jpg",
                "price":"￥9.9",
                "marketPrice":"￥29.9"
            }
        ],
        "curPage":1,
        "rowCount":10,
        "totalRecord":6,
        "totalPage":1
    },
    "tradeId":null
}